logsrvasst/__init__.py
logsrvasst/logsrvasst.py
logsrvasst-0.2.0.dist-info/LICENSE
logsrvasst-0.2.0.dist-info/METADATA
logsrvasst-0.2.0.dist-info/WHEEL
logsrvasst-0.2.0.dist-info/top_level.txt
logsrvasst-0.2.0.dist-info/RECORD
