Metadata-Version: 2.1
Name: logsrvasst
Version: 0.2.0
Summary: Generate server-side configuration for rsyslog
Home-page: https://github.com/titas2003/logsrvasst.git
Author: Titas Majumder
Author-email: titas20031996@gmail.com
License: UNKNOWN
Platform: UNKNOWN
Classifier: Programming Language :: Python :: 3
Classifier: License :: OSI Approved :: MIT License
Classifier: Operating System :: OS Independent
Requires-Python: >=3.6
License-File: LICENSE
